[
  {
    "outputFileName": "wwwroot/Admin/css/AdminStyles.css",
    "inputFiles": [
      "node_modules/bootstrap/dist/css/bootstrap.css",
      "wwwroot/Admin/css/main/components.css",
      "wwwroot/Admin/css/main/main-components.css",
      "wwwroot/Admin/css/main/vertical-menu.css"
    ],
    "minify": {
      "enabled": false,
      "commentMode": "all"
    }
  },
  {
    "outputFileName": "wwwroot/Admin/js/AdminScripts.js",
    "inputFiles": [
      "wwwroot/Admin/js/main/vendor.js",
      "wwwroot/Admin/js/main/app-menu.min.js",
      "wwwroot/Admin/js/main/app.min.js",
      "wwwroot/Admin/js/main/customizer.min.js"
    ],
    "minify": {
      "enabled": false,
      "preserveImportantComments": false
    }
  },
  {
    "outputFileName": "wwwroot/css/SiteStyles.css",
    "inputFiles": [
      "node_modules/bootstrap/dist/css/bootstrap.css"
    ],
    "minify": {
      "enabled": false,
      "commentMode": "all"
    }
  },
  {
    "outputFileName": "wwwroot/js/SiteScripts.js",
    "inputFiles": [
      "node_modules/jquery/dist/jquery.js",
      "node_modules/bootstrap/dist/js/bootstrap.js"
    ],
    "minify": {
      "enabled": false,
      "preserveImportantComments": false
    }
  }
]